Workbook

Sheet Inputs
A1: Thar Sun Power – Base Case Assumptions (fictional)
A2: All amounts in PKR mn unless stated
A4: Installed capacity | B4: MW | C4: 150
A5: Net capacity factor (P50) | B5: % | C5: 0.22
A6: Annual degradation | B6: % | C6: 0.005
A7: Reference tariff (Year 1) | B7: PKR/kWh | C7: 26
A8: Tariff indexation | B8: % | C8: 0.03
A9: O&M cost (Year 1) | B9: PKR mn | C9: 900
A10: Insurance cost (Year 1) | B10: PKR mn | C10: 150
A11: Opex escalation | B11: % | C11: 0.07
A12: EPC cost | B12: PKR mn | C12: 20500
A13: Development costs | B13: PKR mn | C13: 1200
A14: Interest during construction | B14: PKR mn | C14: 1800
A15: Financing fees | B15: PKR mn | C15: 500
A16: Total project cost | B16: PKR mn | C16: =SUM(C12:C15) -> 24000
A17: Senior debt share | B17: % | C17: 0.75
A18: Senior debt | B18: PKR mn | C18: =C16*C17 -> 18000
A19: Sponsor equity | B19: PKR mn | C19: =C16-C18 -> 6000
A20: KIBOR | B20: % | C20: 0.1125
A21: Margin | B21: % | C21: 0.0225
A22: All-in interest rate | B22: % | C22: =C20+C21 -> 0.135
A23: Repayment period | B23: years | C23: 10
A24: Tax rate (exempt) | B24: % | C24: 0
A25: Depreciation life | B25: years | C25: 25

Sheet Operations
A1: Operations
A2: PKR mn
A3: Fiscal year | C3: 2027 | D3: 2028 | E3: 2029 | F3: 2030 | G3: 2031 | H3: 2032 | I3: 2033 | J3: 2034 | K3: 2035 | L3: 2036 | M3: 2037 | N3: 2038
A5: Operating year | B5: # | C5: 1 | D5: =C5+1 -> 2 | E5: =D5+1 -> 3 | F5: =E5+1 -> 4 | G5: =F5+1 -> 5 | H5: =G5+1 -> 6 | I5: =H5+1 -> 7 | J5: =I5+1 -> 8 | K5: =J5+1 -> 9 | ... N5: =M5+1 -> 12
A6: Energy generated | B6: GWh | C6: =Inputs!$C$4*8760*Inputs!$C$5*(1-Inputs!$C$6)^(C5-1)/1000 -> 289.08 | D6: =Inputs!$C$4*8760*Inputs!$C$5*(1-Inputs!$C$6)^(D5-1)/1000 -> 287.6346 | E6: =Inputs!$C$4*8760*Inputs!$C$5*(1-Inputs!$C$6)^(E5-1)/1000 -> 286.19643 | F6: =Inputs!$C$4*8760*Inputs!$C$5*(1-Inputs!$C$6)^(F5-1)/1000 -> 284.76544 | G6: =Inputs!$C$4*8760*Inputs!$C$5*(1-Inputs!$C$6)^(G5-1)/1000 -> 283.34162 | H6: =Inputs!$C$4*8760*Inputs!$C$5*(1-Inputs!$C$6)^(H5-1)/1000 -> 281.92491 | I6: =Inputs!$C$4*8760*Inputs!$C$5*(1-Inputs!$C$6)^(I5-1)/1000 -> 280.51529 | J6: =Inputs!$C$4*8760*Inputs!$C$5*(1-Inputs!$C$6)^(J5-1)/1000 -> 279.11271 | ... N6: =Inputs!$C$4*8760*Inputs!$C$5*(1-Inputs!$C$6)^(N5-1)/1000 -> 273.57218
A7: Tariff | B7: PKR/kWh | C7: =Inputs!$C$7*(1+Inputs!$C$8)^(C5-1) -> 26 | D7: =Inputs!$C$7*(1+Inputs!$C$8)^(D5-1) -> 26.78 | E7: =Inputs!$C$7*(1+Inputs!$C$8)^(E5-1) -> 27.5834 | F7: =Inputs!$C$7*(1+Inputs!$C$8)^(F5-1) -> 28.410902 | G7: =Inputs!$C$7*(1+Inputs!$C$8)^(G5-1) -> 29.263229 | H7: =Inputs!$C$7*(1+Inputs!$C$8)^(H5-1) -> 30.141126 | I7: =Inputs!$C$7*(1+Inputs!$C$8)^(I5-1) -> 31.04536 | J7: =Inputs!$C$7*(1+Inputs!$C$8)^(J5-1) -> 31.976721 | ... N7: =Inputs!$C$7*(1+Inputs!$C$8)^(N5-1) -> 35.990081
A8: Revenue | B8: PKR mn | C8: =C6*C7 -> 7516.08 | D8: =D6*D7 -> 7702.8546 | E8: =E6*E7 -> 7894.2705 | F8: =F6*F7 -> 8090.4431 | G8: =G6*G7 -> 8291.4907 | H8: =H6*H7 -> 8497.5342 | I8: =I6*I7 -> 8708.6979 | J8: =J6*J7 -> 8925.1091 | ... N8: =N6*N7 -> 9845.8849
A10: O&M cost | B10: PKR mn | C10: =Inputs!$C$9*(1+Inputs!$C$11)^(C5-1) -> 900 | D10: =Inputs!$C$9*(1+Inputs!$C$11)^(D5-1) -> 963 | E10: =Inputs!$C$9*(1+Inputs!$C$11)^(E5-1) -> 1030.41 | F10: =Inputs!$C$9*(1+Inputs!$C$11)^(F5-1) -> 1102.5387 | G10: =Inputs!$C$9*(1+Inputs!$C$11)^(G5-1) -> 1179.7164 | H10: 1100 | I10: =Inputs!$C$9*(1+Inputs!$C$11)^(I5-1) -> 1350.6573 | J10: =Inputs!$C$9*(1+Inputs!$C$11)^(J5-1) -> 1445.2033 | K10: =Inputs!$C$9*(1+Inputs!$C$11)^(K5-1) -> 1546.3676 | L10: =Inputs!$C$9*(1+Inputs!$C$11)^(L5-1) -> 1654.6133 | M10: =Inputs!$C$9*(1+Inputs!$C$11)^(M5-1) -> 1770.4362 | N10: =Inputs!$C$9*(1+Inputs!$C$11)^(N5-1) -> 1894.3668
A11: Insurance | B11: PKR mn | C11: =Inputs!$C$10*(1+Inputs!$C$11)^(C5-1) -> 150 | D11: =Inputs!$C$10*(1+Inputs!$C$11)^(D5-1) -> 160.5 | E11: =Inputs!$C$10*(1+Inputs!$C$11)^(E5-1) -> 171.735 | F11: =Inputs!$C$10*(1+Inputs!$C$11)^(F5-1) -> 183.75645 | G11: =Inputs!$C$10*(1+Inputs!$C$11)^(G5-1) -> 196.6194 | H11: =Inputs!$C$10*(1+Inputs!$C$11)^(H5-1) -> 210.38276 | I11: =Inputs!$C$10*(1+Inputs!$C$11)^(I5-1) -> 225.10955 | J11: =Inputs!$C$10*(1+Inputs!$C$11)^(J5-1) -> 240.86722 | K11: =J11*1.05 -> 252.91058 | L11: =Inputs!$C$10*(1+Inputs!$C$11)^(L5-1) -> 275.76888 | M11: =Inputs!$C$10*(1+Inputs!$C$11)^(M5-1) -> 295.0727 | N11: =Inputs!$C$10*(1+Inputs!$C$11)^(N5-1) -> 315.72779
A12: Total operating costs | B12: PKR mn | C12: =C10+C11 -> 1050 | D12: =D10+D11 -> 1123.5 | E12: =E10+E11 -> 1202.145 | F12: =F10+F11 -> 1286.2951 | G12: =G10+G11 -> 1376.3358 | H12: =H10+H11 -> 1310.3828 | I12: =I10+I11 -> 1575.7669 | J12: =J10+J11 -> 1686.0706 | ... N12: =N10+N11 -> 2210.0945
A14: EBITDA | B14: PKR mn | C14: =C8-C12 -> 6466.08 | D14: =D8-D12 -> 6579.3546 | E14: =E8-E12 -> 6692.1255 | F14: =F8-F12 -> 6804.148 | G14: =G8-G12 -> 6915.1548 | H14: =H8-H12 -> 7187.1514 | I14: =I8-I12 -> 7132.9311 | J14: =J8-J12 -> 7239.0385 | ... N14: =N8-N12 -> 7635.7903
A15: EBITDA margin | B15: % | C15: =C14/C8 -> 0.86029952 | D15: =D14/D8 -> 0.85414498 | E15: =E14/E8 -> 0.84771931 | F15: =F14/F8 -> 0.84101054 | G15: =G14/G8 -> 0.83400623 | H15: =H14/H8 -> 0.84579259 | I15: =I14/I8 -> 0.81905827 | J15: =J14/J8 -> 0.81108684 | ... N15: =N14/N8 -> 0.77553114

Sheet Debt Schedule
A1: Senior Debt Schedule
A2: PKR mn
A3: Fiscal year | C3: 2027 | D3: 2028 | E3: 2029 | F3: 2030 | G3: 2031 | H3: 2032 | I3: 2033 | J3: 2034 | K3: 2035 | L3: 2036 | M3: 2037 | N3: 2038
A5: Opening balance | C5: =Inputs!$C$18 -> 18000 | D5: =C7 -> 16200 | E5: =D7 -> 14400 | F5: =E7 -> 12600 | G5: =F7 -> 10800 | H5: =G7 -> 9000 | I5: =H7 -> 7200 | J5: =I7 -> 5400 | K5: =J7 -> 3600 | ... N5: =M7 -> 0
A6: Repayment | C6: =MIN(C5,Inputs!$C$18/Inputs!$C$23) -> 1800 | D6: =MIN(D5,Inputs!$C$18/Inputs!$C$23) -> 1800 | E6: =MIN(E5,Inputs!$C$18/Inputs!$C$23) -> 1800 | F6: =MIN(F5,Inputs!$C$18/Inputs!$C$23) -> 1800 | G6: =MIN(G5,Inputs!$C$18/Inputs!$C$23) -> 1800 | H6: =MIN(H5,Inputs!$C$18/Inputs!$C$23) -> 1800 | I6: =MIN(I5,Inputs!$C$18/Inputs!$C$23) -> 1800 | J6: =MIN(J5,Inputs!$C$18/Inputs!$C$23) -> 1800 | ... N6: =MIN(N5,Inputs!$C$18/Inputs!$C$23) -> 0
A7: Closing balance | C7: =C5-C6 -> 16200 | D7: =D5-D6 -> 14400 | E7: =E5-E6 -> 12600 | F7: =F5-F6 -> 10800 | G7: =G5-G6 -> 9000 | H7: =H5-H6 -> 7200 | I7: =I5-I6 -> 5400 | J7: =J5-J6 -> 3600 | ... N7: =N5-N6 -> 0
A9: Interest | C9: =C5*Inputs!$C$22 -> 2430 | D9: =D5*Inputs!$C$22 -> 2187 | E9: =E5*Inputs!$C$22 -> 1944 | F9: =F5*Inputs!$C$22 -> 1701 | G9: =G5*Inputs!$C$22 -> 1458 | H9: =H5*Inputs!$C$22 -> 1215 | I9: =I5*Inputs!$C$22 -> 972 | J9: =J5*Inputs!$C$22 -> 729 | ... N9: =N5*Inputs!$C$22 -> 0
A10: Total debt service | C10: =C6+C9 -> 4230 | D10: =D6+D9 -> 3987 | E10: =E6+E9 -> 3744 | F10: =F6+F9 -> 3501 | G10: =G6+G9 -> 3258 | H10: =H6+H9 -> 3015 | I10: =I6+I9 -> 2772 | J10: =J6+J9 -> 2529 | ... N10: =N6+N9 -> 0
A12: CFADS | C12: =Operations!C14-'Financial Statements'!C10 -> 6466.08 | D12: =Operations!D14-'Financial Statements'!D10 -> 6579.3546 | E12: =Operations!E14-'Financial Statements'!E10 -> 6692.1255 | F12: =Operations!F14-'Financial Statements'!F10 -> 6804.148 | G12: =Operations!G14-'Financial Statements'!G10 -> 6915.1548 | H12: =Operations!H14-'Financial Statements'!H10 -> 7187.1514 | I12: =Operations!I14-'Financial Statements'!I10 -> 7132.9311 | J12: =Operations!J14-'Financial Statements'!J10 -> 7239.0385 | ... N12: =Operations!N14-'Financial Statements'!N10 -> 7635.7903
A13: DSCR | B13: x | C13: =IF(C10>0,C12/C10,"n/a") -> 1.5286241 | D13: =IF(D10>0,D12/D10,"n/a") -> 1.6502018 | E13: =IF(E10>0,E12/E10,"n/a") -> 1.7874267 | F13: =IF(F10>0,F12/F10,"n/a") -> 1.943487 | G13: =IF(G10>0,G12/G10,"n/a") -> 2.1225153 | H13: =IF(H10>0,H12/H10,"n/a") -> 2.3837982 | I13: =IF(I10>0,I12/I10,"n/a") -> 2.5732075 | J13: =IF(J10>0,J12/J10,"n/a") -> 2.8624114 | ... N13: =IF(N10>0,N12/N10,"n/a") -> n/a

Sheet Financial Statements
A1: Financial Statements
A2: PKR mn
A3: Fiscal year | C3: 2027 | D3: 2028 | E3: 2029 | F3: 2030 | G3: 2031 | H3: 2032 | I3: 2033 | J3: 2034 | K3: 2035 | L3: 2036 | M3: 2037 | N3: 2038
A4: INCOME STATEMENT
A5: Revenue | C5: =Operations!C8 -> 7516.08 | D5: =Operations!D8 -> 7702.8546 | E5: =Operations!E8 -> 7894.2705 | F5: =Operations!F8 -> 8090.4431 | G5: =Operations!G8 -> 8291.4907 | H5: =Operations!H8 -> 8497.5342 | I5: =Operations!I8 -> 8708.6979 | J5: =Operations!J8 -> 8925.1091 | ... N5: =Operations!N8 -> 9845.8849
A6: Operating costs | C6: =-Operations!C12 -> -1050 | D6: =-Operations!D12 -> -1123.5 | E6: =-Operations!E12 -> -1202.145 | F6: =-Operations!F12 -> -1286.2951 | G6: =-Operations!G12 -> -1376.3358 | H6: =-Operations!H12 -> -1310.3828 | I6: =-Operations!I12 -> -1575.7669 | J6: =-Operations!J12 -> -1686.0706 | ... N6: =-Operations!N12 -> -2210.0945
A7: EBITDA | C7: =C5+C6 -> 6466.08 | D7: =D5+D6 -> 6579.3546 | E7: =E5+E6 -> 6692.1255 | F7: =F5+F6 -> 6804.148 | G7: =G5+G6 -> 6915.1548 | H7: =H5+H6 -> 7187.1514 | I7: =I5+I6 -> 7132.9311 | J7: =J5+J6 -> 7239.0385 | ... N7: =N5+N6 -> 7635.7903
A8: Depreciation | C8: =-Inputs!$C$16/Inputs!$C$25 -> -960 | D8: =-Inputs!$C$16/Inputs!$C$25 -> -960 | E8: =-Inputs!$C$16/Inputs!$C$25 -> -960 | F8: =-Inputs!$C$16/Inputs!$C$25 -> -960 | G8: =-Inputs!$C$16/Inputs!$C$25 -> -960 | H8: =-Inputs!$C$16/Inputs!$C$25 -> -960 | I8: =-Inputs!$C$16/Inputs!$C$25 -> -960 | J8: =-Inputs!$C$16/Inputs!$C$25 -> -960 | ... N8: =-Inputs!$C$16/Inputs!$C$25 -> -960
A9: Interest expense | C9: =-'Debt Schedule'!C9 -> -2430 | D9: =-'Debt Schedule'!D9 -> -2187 | E9: =-'Debt Schedule'!E9 -> -1944 | F9: =-'Debt Schedule'!F9 -> -1701 | G9: =-'Debt Schedule'!G9 -> -1458 | H9: =-'Debt Schedule'!H9 -> -1215 | I9: =-'Debt Schedule'!I9 -> -972 | J9: =-'Debt Schedule'!J9 -> -729 | ... N9: =-'Debt Schedule'!N9 -> 0
A10: Tax | C10: =MAX(0,(C7+C8+C9)*Inputs!$C$24) -> 0 | D10: =MAX(0,(D7+D8+D9)*Inputs!$C$24) -> 0 | E10: =MAX(0,(E7+E8+E9)*Inputs!$C$24) -> 0 | F10: =MAX(0,(F7+F8+F9)*Inputs!$C$24) -> 0 | G10: =MAX(0,(G7+G8+G9)*Inputs!$C$24) -> 0 | H10: =MAX(0,(H7+H8+H9)*Inputs!$C$24) -> 0 | I10: =MAX(0,(I7+I8+I9)*Inputs!$C$24) -> 0 | J10: =MAX(0,(J7+J8+J9)*Inputs!$C$24) -> 0 | ... N10: =MAX(0,(N7+N8+N9)*Inputs!$C$24) -> 0
A11: Net profit | C11: =C7+C8+C9-C10 -> 3076.08 | D11: =D7+D8+D9-D10 -> 3432.3546 | E11: =E7+E8+E9-E10 -> 3788.1255 | F11: =F7+F8+F9-F10 -> 4143.148 | G11: =G7+G8+G9-G10 -> 4497.1548 | H11: =H7+H8+H9-H10 -> 5012.1514 | I11: =I7+I8+I9-I10 -> 5200.9311 | J11: =J7+J8+J9-J10 -> 5550.0385 | ... N11: =N7+N8+N9-N10 -> 6675.7903
A13: CASH FLOW
A14: Cash flow before debt service | C14: =C7-C10 -> 6466.08 | D14: =D7-D10 -> 6579.3546 | E14: =E7-E10 -> 6692.1255 | F14: =F7-F10 -> 6804.148 | G14: =G7-G10 -> 6915.1548 | H14: =H7-H10 -> 7187.1514 | I14: =I7-I10 -> 7132.9311 | J14: =J7-J10 -> 7239.0385 | ... N14: =N7-N10 -> 7635.7903
A15: Debt service | C15: =-'Debt Schedule'!C10 -> -4230 | D15: =-'Debt Schedule'!D10 -> -3987 | E15: =-'Debt Schedule'!E10 -> -3744 | F15: =-'Debt Schedule'!F10 -> -3501 | G15: =-'Debt Schedule'!G10 -> -3258 | H15: =-'Debt Schedule'!H10 -> -3015 | I15: =-'Debt Schedule'!I10 -> -2772 | J15: =-'Debt Schedule'!J10 -> -2529 | ... N15: =-'Debt Schedule'!N10 -> 0
A16: Net cash flow | C16: =C14+C15 -> 2236.08 | D16: =D14+D15 -> 2592.3546 | E16: =E14+E15 -> 2948.1255 | F16: =F14+F15 -> 3303.148 | G16: =G14+G15 -> 3657.1548 | H16: =H14+H15 -> 4172.1514 | I16: =I14+I15 -> 4360.9311 | J16: =J14+J15 -> 4710.0385 | ... N16: =N14+N15 -> 7635.7903
A17: Closing cash | C17: =C16 -> 2236.08 | D17: =C17+D16 -> 4828.4346 | E17: =D17+E16 -> 7776.5601 | F17: =E17+F16 -> 11079.708 | G17: =F17+G16 -> 14736.863 | H17: =G17+H16 -> 18909.014 | I17: =H17+I16 -> 23269.945 | J17: =I17+J16 -> 27979.984 | K17: =J17+K16 -> 33041.604 | ... N17: =M17+N16 -> 53619.849
A19: BALANCE SHEET
A20: Net fixed assets | C20: =Inputs!$C$16+C8 -> 23040 | D20: =C20+D8 -> 22080 | E20: =D20+E8 -> 21120 | F20: =E20+F8 -> 20160 | G20: =F20+G8 -> 19200 | H20: =G20+H8 -> 18240 | I20: =H20+I8 -> 17280 | J20: =I20+J8 -> 16320 | K20: =J20+K8 -> 15360 | ... N20: =M20+N8 -> 12480
A21: Cash | C21: =C17 -> 2236.08 | D21: =D17 -> 4828.4346 | E21: =E17 -> 7776.5601 | F21: =F17 -> 11079.708 | G21: =G17 -> 14736.863 | H21: =H17 -> 18909.014 | I21: =I17 -> 23269.945 | J21: =J17 -> 27979.984 | ... N21: =N17 -> 53619.849
A22: Total assets | C22: =C20+C21 -> 25276.08 | D22: =D20+D21 -> 26908.435 | E22: =E20+E21 -> 28896.56 | F22: =F20+F21 -> 31239.708 | G22: =G20+G21 -> 33936.863 | H22: =H20+H21 -> 37149.014 | I22: =I20+I21 -> 40549.945 | J22: =J20+J21 -> 44299.984 | ... N22: =N20+N21 -> 66099.849
A23: Senior debt | C23: ='Debt Schedule'!C7 -> 16200 | D23: ='Debt Schedule'!D7 -> 14400 | E23: ='Debt Schedule'!E7 -> 12600 | F23: ='Debt Schedule'!F7 -> 10800 | G23: ='Debt Schedule'!G7 -> 9000 | H23: ='Debt Schedule'!H7 -> 7200 | I23: ='Debt Schedule'!I7 -> 5400 | J23: ='Debt Schedule'!J7 -> 3600 | ... N23: ='Debt Schedule'!N7 -> 0
A24: Share capital | C24: =Inputs!$C$19 -> 6000 | D24: =Inputs!$C$19 -> 6000 | E24: =Inputs!$C$19 -> 6000 | F24: =Inputs!$C$19 -> 6000 | G24: =Inputs!$C$19 -> 6000 | H24: =Inputs!$C$19 -> 6000 | I24: =Inputs!$C$19 -> 6000 | J24: =Inputs!$C$19 -> 6000 | ... N24: =Inputs!$C$19 -> 6000
A25: Retained earnings | C25: =C11 -> 3076.08 | D25: =C25+D11 -> 6508.4346 | E25: =D25+E11 -> 10296.56 | F25: =E25+F11 -> 14439.708 | G25: =F25+G11 -> 18936.863 | H25: =G25+H11 -> 23949.014 | I25: =H25+I11 -> 29149.945 | J25: =I25+J11 -> 34699.984 | K25: =J25+K11 -> 40601.604 | ... N25: =M25+N11 -> 60099.849
A26: Total liabilities and equity | C26: =C23+C24+C25 -> 25276.08 | D26: =D23+D24+D25 -> 26908.435 | E26: =E23+E24+E25 -> 28896.56 | F26: =F23+F24+F25 -> 31239.708 | G26: =G23+G24+G25 -> 33936.863 | H26: =H23+H24+H25 -> 37149.014 | I26: =I23+I24+I25 -> 40549.945 | J26: =J23+J24+J25 -> 44299.984 | ... N26: =N23+N24+N25 -> 66099.849
A27: Balance check | C27: =C22-C26 -> 0 | D27: =D22-D26 -> 0 | E27: =E22-E26 -> 0 | F27: =F22-F26 -> 0 | G27: =G22-G26 -> 0 | H27: =H22-H26 -> 0 | I27: =I22-I26 -> 0 | J27: =J22-J26 -> 0 | ... N27: =N22-N26 -> 0

Sheet Summary
A1: Key Outputs
A3: Total project cost (PKR mn) | B3: =Inputs!C16 -> 24000
A4: Senior debt (PKR mn) | B4: =Inputs!C18 -> 18000
A5: Sponsor equity (PKR mn) | B5: =Inputs!C19 -> 6000
A6: Minimum DSCR (x) | B6: =MIN('Debt Schedule'!C13:N13) -> 1.5286241
A7: Average DSCR (x) | B7: =AVERAGE('Debt Schedule'!C13:N13) -> 2.3709425
A8: Year 1 EBITDA (PKR mn) | B8: =Operations!C14 -> 6466.08
